Workbook

Sheet Sheet1
A1: BCI Project - Regenerative Cotton Farming
A3: USD $20.46m over 9 years - implementation and MRV costs
A4: (Question: what are costs over the following ~20 years for MRV / maintenance?)
A6: 300,000 farmers | D6: Regenerative farming - tC02 generated per hectare: First 5 years: avg 1.1; next 6-20 years avg 5. Highly variable.
A7: 300000 hectares (?) | D7: Average credit price $16/t, highly variable
A10: Year | B10: FY | C10: Farmers/ hectares total | D10: Farmers/ hectares new | E10: Total (US$ m) | F10: tC02 Y1-5 (total for 5 years) | G10: tC02 Y6-20 (total for 15 years) | H10: Value of credits generated ($16/t)
A11: Y0 | B11: FY2026 | C11: 19000 | D11: 19000 | E11: 0.48 | F11: =5*(D11*1.1) -> 104500 | G11: =15*(D11*5) -> 1425000 | H11: =16*(F11+G11) -> 24472000
A12: Y1 | B12: FY2027 | C12: 28500 | D12: =C12-C11 -> 9500 | E12: 0.69 | F12: =5*(D12*1.1) -> 52250 | G12: =15*(D12*5) -> 712500 | H12: =16*(F12+G12) -> 12236000
A13: Y2 | B13: FY2028 | C13: 44500 | D13: =C13-C12 -> 16000 | E13: 1.05 | F13: =5*(D13*1.1) -> 88000 | G13: =15*(D13*5) -> 1200000 | H13: =16*(F13+G13) -> 20608000
A14: Y3 | B14: FY2029 | C14: 64500 | D14: =C14-C13 -> 20000 | E14: 1.41 | F14: =5*(D14*1.1) -> 110000 | G14: =15*(D14*5) -> 1500000 | H14: =16*(F14+G14) -> 25760000
A15: Y4 | B15: FY2030 | C15: 104500 | D15: =C15-C14 -> 40000 | E15: 2.04 | F15: =5*(D15*1.1) -> 220000 | G15: =15*(D15*5) -> 3000000 | H15: =16*(F15+G15) -> 51520000
A16: Y5 | B16: FY2031 | C16: 144500 | D16: =C16-C15 -> 40000 | E16: 2.46 | F16: =5*(D16*1.1) -> 220000 | G16: =15*(D16*5) -> 3000000 | H16: =16*(F16+G16) -> 51520000
A17: Y6 | B17: FY2032 | C17: 200000 | D17: =C17-C16 -> 55500 | E17: 3.27 | F17: =5*(D17*1.1) -> 305250 | G17: =15*(D17*5) -> 4162500 | H17: =16*(F17+G17) -> 71484000
A18: Y7 | B18: FY2033 | C18: 250000 | D18: =C18-C17 -> 50000 | E18: 4.09 | F18: =5*(D18*1.1) -> 275000 | G18: =15*(D18*5) -> 3750000 | H18: =16*(F18+G18) -> 64400000
A19: Y8 | B19: FY2034 | C19: 300000 | D19: =C19-C18 -> 50000 | E19: 4.97 | F19: =5*(D19*1.1) -> 275000 | G19: =15*(D19*5) -> 3750000 | H19: =16*(F19+G19) -> 64400000
A20: Total | E20: =SUM(E11:E19) -> 20.46 | F20: =SUM(F11:F19) -> 1650000 | G20: =SUM(G11:G19) -> 22500000 | H20: =SUM(H11:H19) -> 386400000
A21: Total tC02 by end of 25 years for all farmers | G21: =SUM(F20:G20) -> 24150000
E23: Revenue minus implementation cost | H23: =H20-20460000 -> 365940000
E24: What are additional costs not incl here?
A26: Hypothetical tree planting programme
A28: $10,000,000 | D28: ARR Removals est Y1-5: 1-3/ha (avg 2); Y6-20: 3-12/ha (avg. 7.5)
A29: 38,000 ha estimate | D29: Avg price $10/t
A30: *These costs are highly estimated, and likely don't take into account additional costs related to a carbon project)
A31: Year | B31: Hectares | C31: tC02 Y1-5 | D31: tC02 Y6-20 | E31: Value of credits generated ($10/t)
A32: 1 | B32: 1000 | C32: =5*(B32*2) -> 10000 | D32: =15*(B32*7.5) -> 112500 | E32: =10*(C32+D32) -> 1225000
A33: 2 | B33: 2000 | C33: =5*(B33*2) -> 20000 | D33: =15*(B33*7.5) -> 225000 | E33: =10*(C33+D33) -> 2450000
A34: 3 | B34: =35000/8 -> 4375 | C34: =5*(B34*2) -> 43750 | D34: =15*(B34*7.5) -> 492187.5 | E34: =10*(C34+D34) -> 5359375
A35: 4 | B35: =35000/8 -> 4375 | C35: =5*(B35*2) -> 43750 | D35: =15*(B35*7.5) -> 492187.5 | E35: =10*(C35+D35) -> 5359375
A36: 5 | B36: =35000/8 -> 4375 | C36: =5*(B36*2) -> 43750 | D36: =15*(B36*7.5) -> 492187.5 | E36: =10*(C36+D36) -> 5359375
A37: 6 | B37: =35000/8 -> 4375 | C37: =5*(B37*2) -> 43750 | D37: =15*(B37*7.5) -> 492187.5 | E37: =10*(C37+D37) -> 5359375
A38: 7 | B38: =35000/8 -> 4375 | C38: =5*(B38*2) -> 43750 | D38: =15*(B38*7.5) -> 492187.5 | E38: =10*(C38+D38) -> 5359375
A39: 8 | B39: =35000/8 -> 4375 | C39: =5*(B39*2) -> 43750 | D39: =15*(B39*7.5) -> 492187.5 | E39: =10*(C39+D39) -> 5359375
A40: 9 | B40: =35000/8 -> 4375 | C40: =5*(B40*2) -> 43750 | D40: =15*(B40*7.5) -> 492187.5 | E40: =10*(C40+D40) -> 5359375
A41: 10 | B41: =35000/8 -> 4375 | C41: =5*(B41*2) -> 43750 | D41: =15*(B41*7.5) -> 492187.5 | E41: =10*(C41+D41) -> 5359375
A42: Total | B42: =SUM(B32:B41) -> 38000 | C42: =SUM(C32:C41) -> 380000 | D42: =SUM(D32:D41) -> 4275000 | E42: =SUM(E32:E41) -> 46550000
A43: Total tC02 at end of 25 years for all plantations (Y35) | D43: =SUM(C42:D42) -> 4655000
A44: Revenue minus cost of implementation | E44: =E42-10000000 -> 36550000 | F44: What additional costs need to be taken into account?

Sheet Input_Agri_srajesh
A1: Dollar to Rupee | B1: 90
A2: Y0 Farmer | B2: 19000
A3: Avg Ha | B3: 1.2
A4: Inflation | B4: 0.05
A5: Credits issuance/ha | B5: 1.8
A6: Starting Price | B6: 18
A7: Profit Sharing | B7: 0.5
A9: # | B9: Cost Head | C9: What’s Included | D9: Freq. | E9: Unit | F9: Assumption (INR) | G9: USD (≈) | H9: Notes / Drivers
A10: 1 | B10: Project design & feasibility | C10: Inception, theory of change, stakeholder mapping, financial model | D10: O | E10: Fixed | F10: 1000000 | G10: =F10/$B$1 -> 11111.111 | H10: Economies of scale → lower at ≥25k ha
A11: 2 | B11: Methodology selection & PD/PD addendum drafting | C11: Method screen, applicability checks, leakage risk analysis | D11: O | E11: Fixed | F11: 3000000 | G11: =F11/$B$1 -> 33333.333 | H11: Varies with standard and baseline complexity
A12: 3 | B12: Legal & farmer onboarding, Plot delineation & GIS | C12: Contracts, consent, KYC, plot mapping, grievance mechanism, GPS/parcel mapping, shapefiles, QA/QC | D12: O | E12: /farmer | F12: 600 | G12: =F12/$B$1 -> 6.6666667 | H12: Convert to /ha by avg. holding size (e.g., 1.2 ha)
A13: 4 | B13: Community engagement & training + input incentives + Field staff & extension (Assumed from current BCI Project) | C13: FFS/ToT, agronomy advisory content, IEC, Input support (e.g., cover crop seed, compost), small tools, FOs, agronomists, supervision, travel | D13: R | E13: /ha | F13: 1600 | G13: =F13/$B$1 -> 17.777778 | H13: Lower with digital delivery; higher for dispersed villages
A14: 5 | B14: Soil sampling & Lab analysis (SOC) | C14: Design, field sampling (0–30 cm), consumables, Dry combustion (LECO/Elemental Analyzer), bulk density | D14: O (Year 0) & periodic (3 yrs) | E14: /sample | F14: 2000 | G14: =F14/$B$1 -> 22.222222 | H14: Assumed 6% from current project heterogenity | J14: =750/12000 -> 0.0625
A15: 6 | B15: Remote sensing & modeling | C15: Activity data, cover/tillage proxies, rainfall/soil covariates, model runs | D15: R | E15: /ha | F15: 50 | G15: =F15/$B$1 -> 0.55555556 | H15: Platform choice & cadence matter
A16: 7 | B16: Digital data systems | C16: Farmer app, MIS, data storage, device depreciation | D16: R | E16: /ha | F16: 6 | G16: =F16/$B$1 -> 0.066666667 | H16: Shared services reduce cost at scale | J16: =1000000/300000 -> 3.3333333
A17: 8 | B17: Third‑party validation | C17: VVB fees, site visit, responses | D17: O (Yr 0) | E17: /tCO₂e (normalized) | F17: 8 | G17: =F17/$B$1 -> 0.088888889 | H17: Convert from lump sum; 1st validation is pricier
A18: 9 | B18: Verification (each issuance) | C18: VVB fees, sampling audit, desk review | D18: R (issuance cycle) | E18: /tCO₂e | F18: 5 | G18: =F18/$B$1 -> 0.055555556 | H18: Depends on volume/issuance frequency
A19: 10 | B19: Registry Account fees | C19: Opening and maintainace | D19: O + R (Yearly) | E19: /Yr | F19: =G19*$B$1 -> 67500 | G19: 750 | H19: Registry‑specific schedules | K19: Project Registration Request Fee: $3,750 (effective Dec 1, 2024, for VCS).
A20: 11 | B20: Pipeline Request Fee | C20: Request to put projects as listed projects | D20: O | E20: Fixed | F20: =G20*$B$1 -> 135000 | G20: 1500 | H20: Registry‑specific schedules
A21: 12 | B21: Validation and Verification Review Fee | C21: At each Va / Ve request | D21: R (Issuance cycle) | E21: Fixed | F21: =G21*$B$1 -> 450000 | G21: 5000 | H21: Registry‑specific schedules
A22: 13 | B22: Project Registration Request Fee: $3,750 (effective Dec 1, 2024, for VCS). | C22: Each Request (Generally Once) | D22: O | E22: Fixed | F22: =G22*$B$1 -> 337500 | G22: 3750 | H22: Registry‑specific schedules
A23: 14 | B23: Issuance Levy | C23: For each issuance | D23: R (per issuance) | E23: /tCO₂e | F23: =G23*$B$1 -> 20.7 | G23: 0.23 | H23: Registry‑specific schedules
A24: 15 | B24: Buffer/risk pool contribution | C24: Non‑tradable credits | D24: R (per issuance) | E24: % of credits | F24: 0.2 | G24: — | H24: Project risk class, methodology rules
A25: 16 | B25: Monitoring & grievance | C25: Helpline, audits, safeguards compliance | D25: R | E25: /ha | F25: 5 | G25: =F25/$B$1 -> 0.055555556 | H25: Safeguards often required by standards/buyers | K25: =1200000/B2 -> 63.157895
A26: 17 | B26: Overheads & management | C26: Finance, HR, audit, management | D26: R | E26: % of direct costs | F26: 0.1 | G26: — | H26: Set band as policy
A27: 18 | B27: Contingency | C27: Unforeseen | D27: R | E27: % of subtotal | F27: 0.05 | G27: — | H27: Apply after overheads
A28: 19 | B28: Taxes | C28: Carbon income tax | D28: R | E28: depends | F28: 0.1 | G28: — | H28: Income tax, brackets and dependency unclear

Sheet Projection_Agri_Srajesh
B3: Years | C3: Total | D3: Y0 | E3: Y1 | F3: Y2 | G3: Y3 | H3: Y4 | I3: Y5 | J3: Y6 | K3: Y7 | L3: Y8 | M3: Y9 | N3: Y10 | O3: Y11 | P3: Y12 | Q3: Y13 | R3: Y14 | S3: Y15 | T3: Y16 | U3: Y17 | V3: Y18 | W3: Y19 | X3: Y20 | Y3: Y21 | Z3: Y22 | AA3: Y23 | AB3: Y24 | AC3: Y25
B4: Farmers | C4: =L4 -> 300000 | D4: 19000 | E4: 28500 | F4: 44500 | G4: 64500 | H4: 104500 | I4: 144500 | J4: 200000 | K4: 250000 | L4: 300000 | M4: 300000 | N4: 300000 | O4: 300000 | P4: 300000 | Q4: 300000 | R4: 300000 | S4: 300000 | T4: 300000 | U4: 300000 | V4: 300000 | W4: 300000 | X4: 300000 | Y4: 300000 | Z4: 300000 | AA4: 300000 | AB4: 300000 | AC4: 300000
B5: Ha | C5: =L5 -> 360000 | D5: =D4*Input_Agri_srajesh!$B$3 -> 22800 | E5: =E4*Input_Agri_srajesh!$B$3 -> 34200 | F5: =F4*Input_Agri_srajesh!$B$3 -> 53400 | G5: =G4*Input_Agri_srajesh!$B$3 -> 77400 | H5: =H4*Input_Agri_srajesh!$B$3 -> 125400 | I5: =I4*Input_Agri_srajesh!$B$3 -> 173400 | J5: =J4*Input_Agri_srajesh!$B$3 -> 240000 | K5: =K4*Input_Agri_srajesh!$B$3 -> 300000 | ... AC5: =AC4*Input_Agri_srajesh!$B$3 -> 360000
B6: Total Credits (Pre Buffer) | C6: =SUM(D6:AC6) -> 13511880 | D6: =D5*Input_Agri_srajesh!$B$5 -> 41040 | E6: =E5*Input_Agri_srajesh!$B$5 -> 61560 | F6: =F5*Input_Agri_srajesh!$B$5 -> 96120 | G6: =G5*Input_Agri_srajesh!$B$5 -> 139320 | H6: =H5*Input_Agri_srajesh!$B$5 -> 225720 | I6: =I5*Input_Agri_srajesh!$B$5 -> 312120 | J6: =J5*Input_Agri_srajesh!$B$5 -> 432000 | K6: =K5*Input_Agri_srajesh!$B$5 -> 540000 | ... AC6: =AC5*Input_Agri_srajesh!$B$5 -> 648000
B7: Total Credits (Post Buffer) | C7: =SUM(D7:AC7) -> 10809504 | D7: =D6*(1-20%) -> 32832 | E7: =E6*(1-20%) -> 49248 | F7: =F6*(1-20%) -> 76896 | G7: =G6*(1-20%) -> 111456 | H7: =H6*(1-20%) -> 180576 | I7: =I6*(1-20%) -> 249696 | J7: =J6*(1-20%) -> 345600 | K7: =K6*(1-20%) -> 432000 | ... AC7: =AC6*(1-20%) -> 518400
B8: Soil Test Cycle | H8: R | L8: R | P8: R | T8: R | X8: R | AB8: R | AC8: R
B9: Issuance Cycle | H9: R | J9: R | L9: R | N9: R | P9: R | R9: R | T9: R | V9: R | X9: R | Z9: R | AB9: R | AC9: R
B10: Inflation | D10: 1 | E10: =D10*(1+Input_Agri_srajesh!$B$4) -> 1.05 | F10: =E10*(1+Input_Agri_srajesh!$B$4) -> 1.1025 | G10: =F10*(1+Input_Agri_srajesh!$B$4) -> 1.157625 | H10: =G10*(1+Input_Agri_srajesh!$B$4) -> 1.2155063 | I10: =H10*(1+Input_Agri_srajesh!$B$4) -> 1.2762816 | J10: =I10*(1+Input_Agri_srajesh!$B$4) -> 1.3400956 | K10: =J10*(1+Input_Agri_srajesh!$B$4) -> 1.4071004 | L10: =K10*(1+Input_Agri_srajesh!$B$4) -> 1.4774554 | ... AC10: =AB10*(1+Input_Agri_srajesh!$B$4) -> 3.3863549
B11: Credit Price | C11: =AVERAGE(D11:AC11) -> 35.386237 | D11: =Input_Agri_srajesh!$B$6*Projection_Agri_Srajesh!D10 -> 18 | E11: =Input_Agri_srajesh!$B$6*Projection_Agri_Srajesh!E10 -> 18.9 | F11: =Input_Agri_srajesh!$B$6*Projection_Agri_Srajesh!F10 -> 19.845 | G11: =Input_Agri_srajesh!$B$6*Projection_Agri_Srajesh!G10 -> 20.83725 | H11: =Input_Agri_srajesh!$B$6*Projection_Agri_Srajesh!H10 -> 21.879113 | I11: =Input_Agri_srajesh!$B$6*Projection_Agri_Srajesh!I10 -> 22.973068 | J11: =Input_Agri_srajesh!$B$6*Projection_Agri_Srajesh!J10 -> 24.121722 | K11: =Input_Agri_srajesh!$B$6*Projection_Agri_Srajesh!K10 -> 25.327808 | ... AC11: =Input_Agri_srajesh!$B$6*Projection_Agri_Srajesh!AC10 -> 60.954389
B13: Total Sale Revenue | C13: =SUM(D13:AC13) -> 4.2218062e+08 | D13: =D7*D11 -> 590976 | E13: =E7*E11 -> 930787.2 | F13: =F7*F11 -> 1526001.1 | G13: =G7*G11 -> 2322436.5 | H13: =H7*H11 -> 3950842.6 | I13: =I7*I11 -> 5736283.2 | J13: =J7*J11 -> 8336467 | K13: =K7*K11 -> 10941613 | ... AC13: =AC7*AC11 -> 31598755
B14: Realised Revenue | H14: =SUM(D13:H13) -> 9321043.5 | J14: =SUM(I13:J13) -> 14072750 | L14: =SUM(K13:L13) -> 24728045 | N14: =SUM(M13:N13) -> 29675295 | P14: =SUM(O13:P13) -> 32717013 | R14: =SUM(Q13:R13) -> 36070507 | T14: =SUM(S13:T13) -> 39767734 | V14: =SUM(U13:V13) -> 43843927 | X14: =SUM(W13:X13) -> 48337929 | Z14: =SUM(Y13:Z13) -> 53292567 | AB14: =SUM(AA13:AB13) -> 58755055 | AC14: =SUM(AC13) -> 31598755
B15: Taxes | C15: =SUM(D15:AC15) -> 42218062 | D15: =Input_Agri_srajesh!$F$28*Projection_Agri_Srajesh!D14 -> 0 | E15: =Input_Agri_srajesh!$F$28*Projection_Agri_Srajesh!E14 -> 0 | F15: =Input_Agri_srajesh!$F$28*Projection_Agri_Srajesh!F14 -> 0 | G15: =Input_Agri_srajesh!$F$28*Projection_Agri_Srajesh!G14 -> 0 | H15: =Input_Agri_srajesh!$F$28*Projection_Agri_Srajesh!H14 -> 932104.35 | I15: =Input_Agri_srajesh!$F$28*Projection_Agri_Srajesh!I14 -> 0 | J15: =Input_Agri_srajesh!$F$28*Projection_Agri_Srajesh!J14 -> 1407275 | K15: =Input_Agri_srajesh!$F$28*Projection_Agri_Srajesh!K14 -> 0 | ... AC15: =Input_Agri_srajesh!$F$28*Projection_Agri_Srajesh!AC14 -> 3159875.5
B16: Total Costs | C16: =SUM(D16:AC16) -> 3.5136157e+08 | D16: =SUM(D24:D40) -> 724446.67 | E16: =SUM(E24:E40) -> 929926 | F16: =SUM(F24:F40) -> 1523961.3 | G16: =SUM(G24:G40) -> 2318725.6 | H16: =SUM(H24:H40) -> 4269980 | I16: =SUM(I24:I40) -> 5725027.6 | J16: =SUM(J24:J40) -> 8527412.6 | K16: =SUM(K24:K40) -> 10917755 | ... AC16: =SUM(AC24:AC40) -> 26414526
B17: Net Revenue | C17: =SUM(D17:AC17) -> 28600990 | D17: =D13-D15-D16 -> -133470.67 | E17: =E13-E15-E16 -> 861.2 | F17: =F13-F15-F16 -> 2039.8533 | G17: =G13-G15-G16 -> 3710.906 | H17: =H13-H15-H16 -> -1251241.8 | I17: =I13-I15-I16 -> 11255.595 | J17: =J13-J15-J16 -> -1598220.7 | K17: =K13-K15-K16 -> 23858.279 | ... AC17: =AC13-AC15-AC16 -> 2024354.1
B18: Profit Sharing @50% | C18: =SUM(D18:AC18) -> 14300495 | D18: =50%*D17 -> -66735.333 | E18: =50%*E17 -> 430.6 | F18: =50%*F17 -> 1019.9267 | G18: =50%*G17 -> 1855.453 | H18: =50%*H17 -> -625620.88 | I18: =50%*I17 -> 5627.7976 | J18: =50%*J17 -> -799110.33 | K18: =50%*K17 -> 11929.14 | ... AC18: =50%*AC17 -> 1012177
B19: Profit Sharing per farmer | C19: =AVERAGE(D19:AC19) -> 1.5088095 | D19: =D18/D4 -> -3.512386 | E19: =E18/E4 -> 0.015108772 | F19: =F18/F4 -> 0.0229197 | G19: =G18/G4 -> 0.028766713 | H19: =H18/H4 -> -5.9868027 | I19: =I18/I4 -> 0.038946696 | J19: =J18/J4 -> -3.9955517 | K19: =K18/K4 -> 0.047716558 | ... AC19: =AC18/AC4 -> 3.3739234
B20: IRR | C20: =IRR(D17:AC17,10) -> 0.20770724
B22: Cost Table
A24: Setting up | B24: Project design & feasibility | C24: =SUM(D24:AC24) -> 11111.111 | D24: =Input_Agri_srajesh!G10 -> 11111.111
B25: Methodology selection & PD/PD addendum drafting | C25: =SUM(D25:AC25) -> 33333.333 | D25: =Input_Agri_srajesh!G11 -> 33333.333
B26: Legal & farmer onboarding, Plot delineation & GIS | C26: =SUM(D26:AC26) -> 10314180 | D26: =Input_Agri_srajesh!$G$12*Projection_Agri_Srajesh!D4*D10 -> 126666.67 | E26: =Input_Agri_srajesh!$G$12*Projection_Agri_Srajesh!E4*E10 -> 199500 | F26: =Input_Agri_srajesh!$G$12*Projection_Agri_Srajesh!F4*F10 -> 327075 | G26: =Input_Agri_srajesh!$G$12*Projection_Agri_Srajesh!G4*G10 -> 497778.75 | H26: =Input_Agri_srajesh!$G$12*Projection_Agri_Srajesh!H4*H10 -> 846802.69 | I26: =Input_Agri_srajesh!$G$12*Projection_Agri_Srajesh!I4*I10 -> 1229484.6 | J26: =Input_Agri_srajesh!$G$12*Projection_Agri_Srajesh!J4*J10 -> 1786794.2 | K26: =Input_Agri_srajesh!$G$12*Projection_Agri_Srajesh!K4*K10 -> 2345167.4 | L26: =Input_Agri_srajesh!$G$12*Projection_Agri_Srajesh!L4*L10 -> 2954910.9
A27: Implmentation | B27: Community engagement & training + input incentives + Field staff & extension (Assumed from current BCI Project) | C27: =SUM(D27:AC27) -> 2.8956147e+08 | D27: =Input_Agri_srajesh!$G$13*Projection_Agri_Srajesh!D5*D10 -> 405333.33 | E27: =Input_Agri_srajesh!$G$13*Projection_Agri_Srajesh!E5*E10 -> 638400 | F27: =Input_Agri_srajesh!$G$13*Projection_Agri_Srajesh!F5*F10 -> 1046640 | G27: =Input_Agri_srajesh!$G$13*Projection_Agri_Srajesh!G5*G10 -> 1592892 | H27: =Input_Agri_srajesh!$G$13*Projection_Agri_Srajesh!H5*H10 -> 2709768.6 | I27: =Input_Agri_srajesh!$G$13*Projection_Agri_Srajesh!I5*I10 -> 3934350.6 | J27: =Input_Agri_srajesh!$G$13*Projection_Agri_Srajesh!J5*J10 -> 5717741.4 | K27: =Input_Agri_srajesh!$G$13*Projection_Agri_Srajesh!K5*K10 -> 7504535.6 | ... AC27: =Input_Agri_srajesh!$G$13*Projection_Agri_Srajesh!AC5*AC10 -> 21672672
B28: Soil sampling & Lab analysis (SOC) | C28: =SUM(D28:AC28) -> 6336530.7 | D28: =Input_Agri_srajesh!$G$14*Input_Agri_srajesh!$J$14*Projection_Agri_Srajesh!D4*Projection_Agri_Srajesh!D10 -> 26388.889 | E28: =IF(E8="R",Input_Agri_srajesh!$G$14*Input_Agri_srajesh!$J$14*Projection_Agri_Srajesh!E4*Projection_Agri_Srajesh!E10,"") | F28: =IF(F8="R",Input_Agri_srajesh!$G$14*Input_Agri_srajesh!$J$14*Projection_Agri_Srajesh!F4*Projection_Agri_Srajesh!F10,"") | G28: =IF(G8="R",Input_Agri_srajesh!$G$14*Input_Agri_srajesh!$J$14*Projection_Agri_Srajesh!G4*Projection_Agri_Srajesh!G10,"") | H28: =IF(H8="R",Input_Agri_srajesh!$G$14*Input_Agri_srajesh!$J$14*Projection_Agri_Srajesh!H4*Projection_Agri_Srajesh!H10,"") -> 176417.23 | I28: =IF(I8="R",Input_Agri_srajesh!$G$14*Input_Agri_srajesh!$J$14*Projection_Agri_Srajesh!I4*Projection_Agri_Srajesh!I10,"") | J28: =IF(J8="R",Input_Agri_srajesh!$G$14*Input_Agri_srajesh!$J$14*Projection_Agri_Srajesh!J4*Projection_Agri_Srajesh!J10,"") | K28: =IF(K8="R",Input_Agri_srajesh!$G$14*Input_Agri_srajesh!$J$14*Projection_Agri_Srajesh!K4*Projection_Agri_Srajesh!K10,"") | L28: =IF(L8="R",Input_Agri_srajesh!$G$14*Input_Agri_srajesh!$J$14*Projection_Agri_Srajesh!L4*Projection_Agri_Srajesh!L10,"") -> 615606.43 | ... AC28: =IF(AC8="R",Input_Agri_srajesh!$G$14*Input_Agri_srajesh!$J$14*Projection_Agri_Srajesh!AC4*Projection_Agri_Srajesh!AC10,"") -> 1410981.2
B29: Remote sensing & modeling | C29: =SUM(D29:AC29) -> 9048795.9 | D29: =Input_Agri_srajesh!$G15*Projection_Agri_Srajesh!D$5*Projection_Agri_Srajesh!D$10 -> 12666.667 | E29: =Input_Agri_srajesh!$G$15*Projection_Agri_Srajesh!E5*Projection_Agri_Srajesh!E10 -> 19950 | F29: =Input_Agri_srajesh!$G$15*Projection_Agri_Srajesh!F5*Projection_Agri_Srajesh!F10 -> 32707.5 | G29: =Input_Agri_srajesh!$G$15*Projection_Agri_Srajesh!G5*Projection_Agri_Srajesh!G10 -> 49777.875 | H29: =Input_Agri_srajesh!$G$15*Projection_Agri_Srajesh!H5*Projection_Agri_Srajesh!H10 -> 84680.269 | I29: =Input_Agri_srajesh!$G$15*Projection_Agri_Srajesh!I5*Projection_Agri_Srajesh!I10 -> 122948.46 | J29: =Input_Agri_srajesh!$G$15*Projection_Agri_Srajesh!J5*Projection_Agri_Srajesh!J10 -> 178679.42 | K29: =Input_Agri_srajesh!$G$15*Projection_Agri_Srajesh!K5*Projection_Agri_Srajesh!K10 -> 234516.74 | L29: =Input_Agri_srajesh!$G$15*Projection_Agri_Srajesh!L5*Projection_Agri_Srajesh!L10 -> 295491.09 | ... AC29: =Input_Agri_srajesh!$G$15*Projection_Agri_Srajesh!AC5*Projection_Agri_Srajesh!AC10 -> 677270.99
B30: Digital data systems | C30: =SUM(D30:AC30) -> 1085855.5 | D30: =Input_Agri_srajesh!$G16*Projection_Agri_Srajesh!D$5*Projection_Agri_Srajesh!D$10 -> 1520 | E30: =Input_Agri_srajesh!$G16*Projection_Agri_Srajesh!E$5*Projection_Agri_Srajesh!E$10 -> 2394 | F30: =Input_Agri_srajesh!$G16*Projection_Agri_Srajesh!F$5*Projection_Agri_Srajesh!F$10 -> 3924.9 | G30: =Input_Agri_srajesh!$G16*Projection_Agri_Srajesh!G$5*Projection_Agri_Srajesh!G$10 -> 5973.345 | H30: =Input_Agri_srajesh!$G16*Projection_Agri_Srajesh!H$5*Projection_Agri_Srajesh!H$10 -> 10161.632 | I30: =Input_Agri_srajesh!$G16*Projection_Agri_Srajesh!I$5*Projection_Agri_Srajesh!I$10 -> 14753.815 | J30: =Input_Agri_srajesh!$G16*Projection_Agri_Srajesh!J$5*Projection_Agri_Srajesh!J$10 -> 21441.53 | K30: =Input_Agri_srajesh!$G16*Projection_Agri_Srajesh!K$5*Projection_Agri_Srajesh!K$10 -> 28142.008 | ... AC30: =Input_Agri_srajesh!$G16*Projection_Agri_Srajesh!AC$5*Projection_Agri_Srajesh!AC$10 -> 81272.519
B31: Third‑party validation | C31: =SUM(D31:AC31) -> 57600 | D31: =Input_Agri_srajesh!$G$17*Projection_Agri_Srajesh!L6 -> 57600
B32: Verification (each issuance) | C32: =SUM(D32:AC32) -> 899223.97 | D32: =IF(D9="R",Input_Agri_srajesh!$G$18*Projection_Agri_Srajesh!D6*Projection_Agri_Srajesh!D10,"") | E32: =IF(E9="R",Input_Agri_srajesh!$G$18*Projection_Agri_Srajesh!E6*Projection_Agri_Srajesh!E10,"") | F32: =IF(F9="R",Input_Agri_srajesh!$G$18*Projection_Agri_Srajesh!F6*Projection_Agri_Srajesh!F10,"") | G32: =IF(G9="R",Input_Agri_srajesh!$G$18*Projection_Agri_Srajesh!G6*Projection_Agri_Srajesh!G10,"") | H32: =IF(H9="R",Input_Agri_srajesh!$G$18*Projection_Agri_Srajesh!H6*Projection_Agri_Srajesh!H10,"") -> 15242.448 | I32: =IF(I9="R",Input_Agri_srajesh!$G$18*Projection_Agri_Srajesh!I6*Projection_Agri_Srajesh!I10,"") | J32: =IF(J9="R",Input_Agri_srajesh!$G$18*Projection_Agri_Srajesh!J6*Projection_Agri_Srajesh!J10,"") -> 32162.295 | K32: =IF(K9="R",Input_Agri_srajesh!$G$18*Projection_Agri_Srajesh!K6*Projection_Agri_Srajesh!K10,"") | ... AC32: =IF(AC9="R",Input_Agri_srajesh!$G$18*Projection_Agri_Srajesh!AC6*Projection_Agri_Srajesh!AC10,"") -> 121908.78
A33: Registry Fees | B33: Registry Account fees | C33: =SUM(D33:AC33) -> 19500 | D33: =Input_Agri_srajesh!$G$19 -> 750 | E33: =Input_Agri_srajesh!$G$19 -> 750 | F33: =Input_Agri_srajesh!$G$19 -> 750 | G33: =Input_Agri_srajesh!$G$19 -> 750 | H33: =Input_Agri_srajesh!$G$19 -> 750 | I33: =Input_Agri_srajesh!$G$19 -> 750 | J33: =Input_Agri_srajesh!$G$19 -> 750 | K33: =Input_Agri_srajesh!$G$19 -> 750 | ... AC33: =Input_Agri_srajesh!$G$19 -> 750
B34: Pipeline Request Fee | C34: =SUM(D34:AC34) -> 1500 | D34: =Input_Agri_srajesh!G20 -> 1500
B35: Validation and Verification Review Fee | C35: =SUM(D35:AC35) -> 60000 | D35: =IF(D$9="R",Input_Agri_srajesh!$G$21,"") | E35: =IF(E$9="R",Input_Agri_srajesh!$G$21,"") | F35: =IF(F$9="R",Input_Agri_srajesh!$G$21,"") | G35: =IF(G$9="R",Input_Agri_srajesh!$G$21,"") | H35: =IF(H$9="R",Input_Agri_srajesh!$G$21,"") -> 5000 | I35: =IF(I$9="R",Input_Agri_srajesh!$G$21,"") | J35: =IF(J$9="R",Input_Agri_srajesh!$G$21,"") -> 5000 | K35: =IF(K$9="R",Input_Agri_srajesh!$G$21,"") | ... AC35: =IF(AC$9="R",Input_Agri_srajesh!$G$21,"") -> 5000
B36: Project Registration Request Fee: $3,750 (effective Dec 1, 2024, for VCS). | C36: =SUM(D36:AC36) -> 3750 | D36: =Input_Agri_srajesh!G22 -> 3750
B37: Issuance Levy | C37: =SUM(D37:AC37) -> 3107732.4 | H37: =SUM(D49:H49) -> 129664.8 | J37: =SUM(I49:J49) -> 171147.6 | L37: =SUM(K49:L49) -> 273240 | N37: =SUM(M49:N49) -> 298080 | P37: =SUM(O49:P49) -> 298080 | R37: =SUM(Q49:R49) -> 298080 | T37: =SUM(S49:T49) -> 298080 | V37: =SUM(U49:V49) -> 298080 | X37: =SUM(W49:X49) -> 298080 | Z37: =SUM(Y49:Z49) -> 298080 | AB37: =SUM(AA49:AB49) -> 298080 | AC37: =SUM(AC49) -> 149040
A38: Admin | B38: Monitoring & grievance | C38: =SUM(D38:AC38) -> 417033.33 | D38: =Input_Agri_srajesh!$G$25*Projection_Agri_Srajesh!D5*D10 -> 1266.6667 | E38: =Input_Agri_srajesh!$G$25*Projection_Agri_Srajesh!E5 -> 1900 | F38: =Input_Agri_srajesh!$G$25*Projection_Agri_Srajesh!F5 -> 2966.6667 | G38: =Input_Agri_srajesh!$G$25*Projection_Agri_Srajesh!G5 -> 4300 | H38: =Input_Agri_srajesh!$G$25*Projection_Agri_Srajesh!H5 -> 6966.6667 | I38: =Input_Agri_srajesh!$G$25*Projection_Agri_Srajesh!I5 -> 9633.3333 | J38: =Input_Agri_srajesh!$G$25*Projection_Agri_Srajesh!J5 -> 13333.333 | K38: =Input_Agri_srajesh!$G$25*Projection_Agri_Srajesh!K5 -> 16666.667 | L38: =Input_Agri_srajesh!$G$25*Projection_Agri_Srajesh!L5 -> 20000 | ... AC38: =Input_Agri_srajesh!$G$25*Projection_Agri_Srajesh!AC5 -> 20000
B39: Overheads & management | C39: =SUM(D39:AC39) -> 28956147 | D39: =Input_Agri_srajesh!$F$26*D27 -> 40533.333 | E39: =Input_Agri_srajesh!$F$26*E27 -> 63840 | F39: =Input_Agri_srajesh!$F$26*F27 -> 104664 | G39: =Input_Agri_srajesh!$F$26*G27 -> 159289.2 | H39: =Input_Agri_srajesh!$F$26*H27 -> 270976.86 | I39: =Input_Agri_srajesh!$F$26*I27 -> 393435.06 | J39: =Input_Agri_srajesh!$F$26*J27 -> 571774.14 | K39: =Input_Agri_srajesh!$F$26*K27 -> 750453.56 | ... AC39: =Input_Agri_srajesh!$F$26*AC27 -> 2167267.2
B40: Contingency | C40: =SUM(D40:AC40) -> 1447807.3 | D40: =Input_Agri_srajesh!$F$27*D39 -> 2026.6667 | E40: =Input_Agri_srajesh!$F$27*E39 -> 3192 | F40: =Input_Agri_srajesh!$F$27*F39 -> 5233.2 | G40: =Input_Agri_srajesh!$F$27*G39 -> 7964.46 | H40: =Input_Agri_srajesh!$F$27*H39 -> 13548.843 | I40: =Input_Agri_srajesh!$F$27*I39 -> 19671.753 | J40: =Input_Agri_srajesh!$F$27*J39 -> 28588.707 | K40: =Input_Agri_srajesh!$F$27*K39 -> 37522.678 | ... AC40: =Input_Agri_srajesh!$F$27*AC39 -> 108363.36
B49: Issuance Levy | D49: =D6*Input_Agri_srajesh!$G$23 -> 9439.2 | E49: =E6*Input_Agri_srajesh!$G$23 -> 14158.8 | F49: =F6*Input_Agri_srajesh!$G$23 -> 22107.6 | G49: =G6*Input_Agri_srajesh!$G$23 -> 32043.6 | H49: =H6*Input_Agri_srajesh!$G$23 -> 51915.6 | I49: =I6*Input_Agri_srajesh!$G$23 -> 71787.6 | J49: =J6*Input_Agri_srajesh!$G$23 -> 99360 | K49: =K6*Input_Agri_srajesh!$G$23 -> 124200 | ... AC49: =AC6*Input_Agri_srajesh!$G$23 -> 149040
